shri_ram_bhasa/__init__.py
shri_ram_bhasa/ramji.py
shri_ram_bhasa-0.10.dist-info/METADATA
shri_ram_bhasa-0.10.dist-info/WHEEL
shri_ram_bhasa-0.10.dist-info/entry_points.txt
shri_ram_bhasa-0.10.dist-info/top_level.txt
shri_ram_bhasa-0.10.dist-info/RECORD
